{
  "ustv": [
      
      {
      "id": "usanetwork",
      "logo": "https://i.imgur.com/qwxOuOb.jpeg",
      "kategori": "aaa",
      "name": "usanetwork",
      "protokol": "https",
      "url": "cdn2.aluku91.foundation/usa-usanetwork.m3u8",
      "ref": "https://365streamtv.live/"
    },
    {
      "id": "fubosport",
      "logo": "https://i.imgur.com/qCuwz1s.jpeg",
      "kategori": "popular",
      "name": "fubosport",
      "protokol": "https",
      "url": "cdn2.aluku91.foundation/usa-fubosport.m3u8",
      "ref": "https://365streamtv.live/"
    },
    {
      "id": "Starsportselect1",
      "logo": "https://f-srv-01.tiksports.net/images/logos/channels/zstarsportselect1.png",
      "kategori": "",
      "name": "Starsportselect1",
      "protokol": "https",
      "url": "yuvraj43.xyz/TP-worldwide/manifest.mpd?id=246|drmScheme=clearkey&drmLicense=http://yuvraj.fun/tp-keys/key.php?id=246",
      "useragent": "Mozilla/5.0",
      "ref": ""
    },
    {
      "id": "Starsportselect2",
      "logo": "https://f-srv-01.tiksports.net/images/logos/channels/zstarsportselect2.png",
      "kategori": "",
      "name": "Starsportselect2",
      "protokol": "https",
      "url": "yuvraj43.xyz/TP-worldwide/manifest.mpd?id=463|drmScheme=clearkey&drmLicense=http://yuvraj.fun/tp-keys/key.php?id=463",
      "useragent": "Mozilla/5.0",
      "ref": ""
    },
    {
      "id": "Tv85",
      "logo": "https://i.imgur.com/4R7H7Bi.jpeg",
      "kategori": "popular",
      "name": "Tv85",
      "protokol": "https",
      "url": "hw1.jemtv.com/app/tv85/chunks.m3u8",
      "ref": ""
    },
    {
      "id": "Tnt1_365",
      "logo": "https://i.imgur.com/RZhlWCD.jpeg",
      "kategori": "popular",
      "name": "TNT1",
      "protokol": "https",
      "url": "cdn2.aluku91.foundation/uk-tntsport1.m3u8",
      "ref": "https://365streamtv.live/"
    },
    {
      "id": "Tnt2_365",
      "logo": "https://i.imgur.com/a2o9OcX.jpeg",
      "kategori": "popular",
      "name": "TNT2",
      "protokol": "https",
      "url": "cdn2.aluku91.foundation/uk-tntsport2.m3u8",
      "ref": "https://365streamtv.live/"
    },
    {
      "id": "Tnt3_365",
      "logo": "https://i.imgur.com/AgyzJHa.jpeg",
      "kategori": "popular",
      "name": "TNT3",
      "protokol": "https",
      "url": "cdn2.aluku91.foundation/uk-tntsport3.m3u8",
      "ref": "https://365streamtv.live/"
    },
    {
      "id": "Tnt4_365",
      "logo": "https://i.imgur.com/CYox558.jpeg",
      "kategori": "popular",
      "name": "TNT4",
      "protokol": "https",
      "url": "cdn2.aluku91.foundation/uk-tntsport4.m3u8",
      "ref": "https://365streamtv.live/"
    },
    {
      "id": "NBC_US",
      "logo": "https://i.imgur.com/yPemEO1.jpeg",
      "kategori": "popular",
      "name": "NBC",
      "protokol": "https",
      "url": "cdn.aluku91.foundation/us-nbatv.m3u8",
      "ref": "https://365streamtv.live/"
    },
    {
      "id": "BBCAmerica_US",
      "logo": "https://i.imgur.com/fFtdVZd.jpeg",
      "kategori": "popular",
      "name": "BBC America",
      "protokol": "https",
      "url": "cdn.aluku91.foundation/uk-bbcnews.m3u8",
      "ref": "https://365streamtv.live/"
    },
    {
      "id": "FS1_US",
      "logo": "https://i.imgur.com/xMXgMSy.jpeg",
      "kategori": "popular",
      "name": "Fox Sport 1",
      "protokol": "https",
      "url": "cdn.aluku91.foundation/usa-fs1.m3u8",
      "ref": "https://365streamtv.live/"
    },
    {
      "id": "FS2_US",
      "logo": "https://i0.wp.com/tv247.us/wp-content/uploads/2020/07/FS2.png",
      "kategori": "popular",
      "name": "Fox Sport 2",
      "protokol": "https",
      "url": "cdn.aluku91.foundation/usa-fs2.m3u8",
      "ref": "https://365streamtv.live/"
    },
    {
      "id": "HBO_US",
      "logo": "https://i2.wp.com/tv247.us/wp-content/uploads/2020/07/HBO-1.png",
      "kategori": "popular",
      "name": "HBO",
      "protokol": "https",
      "url": "cdn4.aluku91.foundation/ent-hbo.m3u8",
      "ref": "https://365streamtv.live/"
    },
    {
      "id": "CINEMAX_US",
      "logo": "https://i1.wp.com/tv247.us/wp-content/uploads/2021/02/cinemax-movie-max.png",
      "kategori": "",
      "name": "Cinemax",
      "protokol": "https",
      "url": "live.tv247us.com/tv247/cinemaxus.m3u8",
      "ref": "https://365streamtv.live/"
    },
    {
      "id": "BigTenNetwork_US",
      "logo": "https://i0.wp.com/tv247.us/wp-content/uploads/2020/09/btn.png",
      "kategori": "",
      "name": "Big Ten Network",
      "protokol": "https",
      "url": "live.tv247us.com/tv247/btn.m3u8",
      "ref": "https://365streamtv.live/"
    },
    {
      "id": "FOX_US",
      "logo": "https://f-srv-01.tiksports.net/images/logos/channels/cdnusafox-channel.svg",
      "kategori": "popular",
      "name": "Fox",
      "protokol": "https",
      "url": "cdn2.aluku91.foundation/usa-fs2.m3u8",
      "ref": "https://365streamtv.live/"
    },
    {
      "id": "NFLRedzone_US",
      "logo": "https://i0.wp.com/tv247.us/wp-content/uploads/2020/09/NFL-REDZONE-From-NFL-NW.png",
      "kategori": "popular",
      "name": "NFL Redzone",
      "protokol": "https",
      "url": "cdn.aluku91.foundation/us-nfl.m3u8",
      "ref": "https://365streamtv.live/"
    },
    {
      "id": "MLBNetwork_US",
      "logo": "https://i1.wp.com/tv247.us/wp-content/uploads/2020/07/MLB-Network.png",
      "kategori": "",
      "name": "MLB Network",
      "protokol": "https",
      "url": "live.tv247us.com/tv247/mlb.m3u8",
      "ref": "https://365streamtv.live/"
    },
    {
      "id": "NBATV_US",
      "logo": "https://i0.wp.com/tv247.us/wp-content/uploads/2020/07/NBATV-2.png",
      "kategori": "popular",
      "name": "NBA TV",
      "protokol": "https",
      "url": "cdn.aluku91.foundation/us-nbatv.m3u8",
      "ref": "https://365streamtv.live/"
    },
    {
      "id": "Nicktoons_US",
      "logo": "https://i0.wp.com/tv247.us/wp-content/uploads/2021/02/NICKTOONS.png",
      "kategori": "",
      "name": "Nicktoons",
      "protokol": "https",
      "url": "live.tv247us.com/tv247/nicktoons.m3u8",
      "ref": "https://365streamtv.live/"
    },
    {
      "id": "CNBC_US",
      "logo": "https://i1.wp.com/tv247.us/wp-content/uploads/2020/01/CNBC.png",
      "kategori": "",
      "name": "CNBC",
      "protokol": "https",
      "url": "live.tv247us.com/tv247/cnbc.m3u8",
      "ref": "https://365streamtv.live/"
    },
    {
      "id": "CBSSportsNetwork_US",
      "logo": "https://i2.wp.com/tv247.us/wp-content/uploads/2021/02/CBS-Network-free-live-stream.png",
      "kategori": "popular",
      "name": "CBS Sports Network",
      "protokol": "https",
      "url": "cdn2.aluku91.foundation/usa-cbssport.m3u8",
      "ref": "https://365streamtv.live/"
    },
    {
      "id": "NickelodeonTV_US",
      "logo": "https://i1.wp.com/tv247.us/wp-content/uploads/2021/02/Nickelodeon-free-live-stream.png",
      "kategori": "",
      "name": "Nickelodeon TV",
      "protokol": "https",
      "url": "live.tv247us.com/tv247/nickelodeon.m3u8",
      "ref": "https://365streamtv.live/"
    },
    {
      "id": "AE_US",
      "logo": "https://i0.wp.com/tv247.us/wp-content/uploads/2021/02/AE-free-live-stream.png",
      "kategori": "",
      "name": "A&E",
      "protokol": "https",
      "url": "live.tv247us.com/tv247/ae.m3u8",
      "ref": "https://tv247.us/"
    },
    {
      "id": "TBS_US",
      "logo": "https://i2.wp.com/tv247.us/wp-content/uploads/2021/02/TBS-free-live-stream.png",
      "kategori": "",
      "name": "TBS",
      "protokol": "https",
      "url": "live.tv247us.com/tv247/tbs.m3u8",
      "ref": "https://tv247.us/"
    },
    {
      "id": "HallmarkMoviesMysteriesTV_US",
      "logo": "https://i2.wp.com/tv247.us/wp-content/uploads/2021/02/HALLMARK-MOVIES-MYSTERIES-free-live-stream.png",
      "kategori": "",
      "name": "Hallmark Movies & Mysteries TV",
      "protokol": "https",
      "url": "live.tv247us.com/tv247/hallmarkmm.m3u8",
      "ref": "https://tv247.us/"
    },
    {
      "id": "Hallmark_US",
      "logo": "https://i2.wp.com/tv247.us/wp-content/uploads/2021/02/Hallmark-Channel-free-live-stream.png",
      "kategori": "",
      "name": "Hallmark",
      "protokol": "https",
      "url": "live.tv247us.com/tv247/hallmark.m3u8",
      "ref": "https://tv247.us/"
    },
    {
      "id": "BET_US",
      "logo": "https://i1.wp.com/tv247.us/wp-content/uploads/2021/02/bet.png",
      "kategori": "",
      "name": "BET",
      "protokol": "https",
      "url": "live.tv247us.com/tv247/bet.m3u8",
      "ref": "https://tv247.us/"
    },
    {
      "id": "ComedyCentral_US",
      "logo": "https://i2.wp.com/tv247.us/wp-content/uploads/2021/02/Comedy-Central-free-live-stream.png",
      "kategori": "",
      "name": "Comedy Central",
      "protokol": "https",
      "url": "live.tv247us.com/tv247/comedy.m3u8",
      "ref": "https://tv247.us/"
    },
    {
      "id": "NASA_US",
      "logo": "https://i1.wp.com/tv247.us/wp-content/uploads/2021/02/NASA-TV-FREE-LIVE-STREAM-TV247-US.png",
      "kategori": "",
      "name": "Nasa",
      "protokol": "https",
      "url": "ntv1.akamaized.net/hls/live/2014075/NASA-NTV1-HLS/master.m3u8",
      "ref": ""
    },
    {
      "id": "MAVTV_US",
      "logo": "https://i1.wp.com/tv247.us/wp-content/uploads/2020/07/xdqukd.png",
      "kategori": "",
      "name": "MAVTV",
      "protokol": "https",
      "url": "mavtv-1.sinclair.wurl.com/manifest/playlist.m3u8",
      "ref": "https://tv247.us/"
    },
    {
      "id": "PBS_US",
      "logo": "https://i0.wp.com/tv247.us/wp-content/uploads/2020/07/eqanuc-1.png",
      "kategori": "",
      "name": "PBS",
      "protokol": "https",
      "url": "mavtv-1.sinclair.wurl.com/manifest/playlist.m3u8",
      "ref": "https://tv247.us/"
    },
    {
      "id": "TennisChannel_US",
      "logo": "https://i2.wp.com/tv247.us/wp-content/uploads/2021/06/Tennis-channel.png",
      "kategori": "popular",
      "name": "Tennis Channel",
      "protokol": "https",
      "url": "cdn.aluku91.foundation/us-tennistv.m3u8",
      "useragent": "Mozilla/5.0",
      "ref": "https://365streamtv.live/"
    },
    {
      "id": "NFLREDZONE_US",
      "logo": "https://i0.wp.com/tv247.us/wp-content/uploads/2020/08/NFL-network.png",
      "kategori": "",
      "name": "NFL REDZONE",
      "protokol": "https",
      "url": "webudit.hlsjs.ru/lb/wiki114/index.m3u8",
      "useragent": "android",
      "ref": ""
    },
    {
      "id": "TruTV_US",
      "logo": "https://i0.wp.com/tv247.us/wp-content/uploads/2023/02/trutv-free-live-stream-tv247-us.png",
      "kategori": "",
      "name": "TruTV",
      "protokol": "https",
      "url": "live.tv247us.com/tv247/trutv.m3u8",
      "useragent": "android",
      "ref": "https://tv247.us/"
    },
    {
      "id": "Oxygen_US",
      "logo": "https://i1.wp.com/tv247.us/wp-content/uploads/2021/02/Oxygen-free-live-stream.png",
      "kategori": "",
      "name": "Oxygen",
      "protokol": "https",
      "url": "live.tv247us.com/tv247/oxygen.m3u8",
      "useragent": "android",
      "ref": "https://tv247.us/"
    },
    {
      "id": "CartoonNetwork_US",
      "logo": "https://i0.wp.com/tv247.us/wp-content/uploads/2020/07/Cartoon-Network.png",
      "kategori": "",
      "name": "Cartoon Network",
      "protokol": "https",
      "url": "live.tv247us.com/tv247/cn.m3u8",
      "useragent": "android",
      "ref": "https://tv247.us/"
    },
    {
      "id": "CNN_US",
      "logo": "https://i0.wp.com/tv247.us/wp-content/uploads/2020/12/CNN.png",
      "kategori": "",
      "name": "CNN",
      "protokol": "https",
      "url": "cnn-cnninternational-1-eu.rakuten.wurl.tv/playlist.m3u8",
      "useragent": "android",
      "ref": ""
    },
    {
      "id": "NationalGeographic_US",
      "logo": "https://i1.wp.com/tv247.us/wp-content/uploads/2020/01/National-Geographic.png",
      "kategori": "",
      "name": "National Geographic",
      "protokol": "https",
      "url": "live.tv247us.com/tv247/national.m3u8",
      "useragent": "android",
      "ref": "https://tv247.us/"
    },
    {
      "id": "AMC_US",
      "logo": "https://i2.wp.com/tv247.us/wp-content/uploads/2020/12/amc-free-online.png",
      "kategori": "",
      "name": "AMC",
      "protokol": "https",
      "url": "live.tv247us.com/tv247/amc.m3u8",
      "useragent": "android",
      "ref": "https://tv247.us/"
    },
    {
      "id": "VH1_US",
      "logo": "https://i1.wp.com/tv247.us/wp-content/uploads/2021/07/VH1.png",
      "kategori": "",
      "name": "VH1",
      "protokol": "https",
      "url": "content.uplynk.com/channel/36953f5b6546464590d2fcd954bc89cf.m3u8",
      "useragent": "android",
      "ref": ""
    },
    {
      "id": "ESPN_US",
      "logo": "https://i2.wp.com/tv247.us/wp-content/uploads/2019/11/ESPN.png",
      "kategori": "popular",
      "name": "ESPN",
      "protokol": "https",
      "url": "cdn.aluku91.foundation/us-espn.m3u8",
      "useragent": "android",
      "ref": "https://365streamtv.live/"
    },
    {
      "id": "ESPN 2_US",
      "logo": "https://i0.wp.com/tv247.us/wp-content/uploads/2019/11/ESPN-2.png",
      "kategori": "",
      "name": "ESPN 2",
      "protokol": "https",
      "url": "live.tv247us.com/tv247/e2.m3u8",
      "useragent": "android",
      "ref": "https://tv247.us/"
    },
    {
      "id": "ESPN3_US",
      "logo": "https://i0.wp.com/tv247.us/wp-content/uploads/2019/11/ESPN-3.png",
      "kategori": "",
      "name": "ESPN3",
      "protokol": "https",
      "url": "live.tv247us.com/tv247/espn.m3u8",
      "useragent": "android",
      "ref": "https://tv247.us/"
    },
    {
      "id": "ESPNU_US",
      "logo": "https://i0.wp.com/tv247.us/wp-content/uploads/2019/11/espnU.png",
      "kategori": "",
      "name": "ESPN U",
      "protokol": "https",
      "url": "cdn.espnfreenew.xyz/channel/sec.m3u8",
      "useragent": "android",
      "ref": ""
    },
    {
      "id": "TNT_US",
      "logo": "https://i0.wp.com/tv247.us/wp-content/uploads/2020/08/TNT-US.png",
      "kategori": "",
      "name": "TNT",
      "protokol": "https",
      "url": "live.tv247us.com/tv247/tnt.m3u8",
      "useragent": "android",
      "ref": "https://tv247.us/"
    },
    {
      "id": "History_US",
      "logo": "https://i0.wp.com/tv247.us/wp-content/uploads/2021/02/History.png",
      "kategori": "",
      "name": "History (American TV network)",
      "protokol": "https",
      "url": "live.tv247us.com/tv247/history.m3u8",
      "useragent": "android",
      "ref": "https://tv247.us/"
    },
    {
      "id": "DiscoveryChannel_US",
      "logo": "https://i0.wp.com/tv247.us/wp-content/uploads/2020/01/discovery-channel.png",
      "kategori": "popular",
      "name": "Discovery Channel",
      "protokol": "https",
      "url": "cdn4.aluku91.foundation/ent-discovery.m3u8",
      "useragent": "Mozilla/5.0",
      "ref": "https://365streamtv.live/"
    },
    {
      "id": "MTV_US",
      "logo": "https://i0.wp.com/tv247.us/wp-content/uploads/2019/11/MTV.png",
      "kategori": "",
      "name": "MTV",
      "protokol": "https",
      "url": "live.tv247us.com/tv247/mtv.m3u8",
      "useragent": "android",
      "ref": "https://tv247.us/"
    },
    {
      "id": "DisneyJunior_US",
      "logo": "https://i1.wp.com/tv247.us/wp-content/uploads/2019/11/Disney-Junior.png",
      "kategori": "",
      "name": "Disney Junior",
      "protokol": "https",
      "url": "cdn.espnfreenew.xyz/channel/disneyjunior.m3u8",
      "useragent": "android",
      "ref": ""
    },
    {
      "id": "DisneyXD_US",
      "logo": "https://i0.wp.com/tv247.us/wp-content/uploads/2019/11/Disney-XD.png",
      "kategori": "",
      "name": "DisneyXD",
      "protokol": "https",
      "url": "cdn.espnfreenew.xyz/channel/disneyxd.m3u8",
      "useragent": "android",
      "ref": ""
    },
    {
      "id": "DisneyChannel_US",
      "logo": "https://i2.wp.com/tv247.us/wp-content/uploads/2019/11/Disney-Channel.png",
      "kategori": "",
      "name": "Disney Channel",
      "protokol": "https",
      "url": "e3.thetvapp.to/hls/DisneyChannelEast.m3u8?token=4XzVdppuncuzHmZ2e78upg&expires=1695741031",
      "useragent": "android",
      "ref": ""
    },
    {
      "id": "SECNetwork_US",
      "logo": "https://i1.wp.com/tv247.us/wp-content/uploads/2019/11/Sec-network.png",
      "kategori": "",
      "name": "SEC Network",
      "protokol": "https",
      "url": "cdn.espnfreenew.xyz/channel/sec.m3u8",
      "useragent": "android",
      "ref": ""
    },
    {
      "id": "ACCNetwork_US",
      "logo": "https://i0.wp.com/tv247.us/wp-content/uploads/2019/11/accn.png",
      "kategori": "",
      "name": "ACC Network",
      "protokol": "https",
      "url": "cdn.espnfreenew.xyz/channel/sec.m3u8",
      "useragent": "android",
      "ref": ""
    },
    {
      "id": "TravelChannel_US",
      "logo": "https://i0.wp.com/tv247.us/wp-content/uploads/2021/02/travel-channel-free-live-stream-1.png",
      "kategori": "",
      "name": "Travel Channel",
      "protokol": "https",
      "url": "live.tv247us.com/tv247/travel.m3u8",
      "useragent": "android",
      "ref": "https://tv247.us/"
    },
    {
      "id": "tnt",
      "logo": "https://f-srv-01.tiksports.net/images/logos/channels/tnt-usa.png",
      "kategori": "popular",
      "name": "tnt",
      "protokol": "https",
      "url": "cdn4.aluku91.foundation/line3.m3u8",
      "useragent": "",
      "ref": "https://365streamtv.live/"
    }
  ]
}